agent_generator/__init__.py
agent_generator/cli.py
agent_generator/config.py
agent_generator/wsgi.py
agent_generator/data/default_prompts.yaml
agent_generator/frameworks/__init__.py
agent_generator/frameworks/base.py
agent_generator/frameworks/crewai/__init__.py
agent_generator/frameworks/crewai/generator.py
agent_generator/frameworks/crewai_flow/__init__.py
agent_generator/frameworks/crewai_flow/generator.py
agent_generator/frameworks/langgraph/__init__.py
agent_generator/frameworks/langgraph/generator.py
agent_generator/frameworks/react/__init__.py
agent_generator/frameworks/react/generator.py
agent_generator/frameworks/watsonx_orchestrate/__init__.py
agent_generator/frameworks/watsonx_orchestrate/generator.py
agent_generator/models/__init__.py
agent_generator/models/agent.py
agent_generator/models/task.py
agent_generator/models/workflow.py
agent_generator/providers/__init__.py
agent_generator/providers/base.py
agent_generator/providers/openai_provider.py
agent_generator/providers/watsonx_provider.py
agent_generator/utils/__init__.py
agent_generator/utils/logger.py
agent_generator/utils/parser.py
agent_generator/utils/prompts.py
agent_generator/utils/visualizer.py
agent_generator/web/__init__.py
agent_generator/web/routes/__init__.py
agent_generator/web/routes/api.py
agent_generator/web/routes/main.py
agent_generator/web/static/css/main.css
agent_generator/web/static/js/graph.js
agent_generator/web/templates/base.html
agent_generator/web/templates/index.html
agent_generator/web/templates/visualization.html
agent_generator-0.1.2.dist-info/METADATA
agent_generator-0.1.2.dist-info/WHEEL
agent_generator-0.1.2.dist-info/entry_points.txt
agent_generator-0.1.2.dist-info/licenses/LICENSE
agent_generator-0.1.2.dist-info/RECORD
