Metadata-Version: 2.4
Name: agent-generator
Version: 0.1.2
Summary: Turn plain‑English requirements into fully‑configured multi‑agent AI teams (CrewAI, LangGraph, ReAct, WatsonX Orchestrate).
Project-URL: Homepage, https://github.com/ruslanmv/agent-generator
Project-URL: Repository, https://github.com/ruslanmv/agent-generator
Project-URL: Issues, https://github.com/ruslanmv/agent-generator/issues
Author-email: "Ruslan M. V." <contact@ruslanmv.com>
License: Copyright 2025 ruslanmv.com
License-File: LICENSE
Keywords: LLM,crew-ai,langchain,multi-agent,orchestrate,watsonx-ai
Classifier: Development Status :: 3 - Alpha
Classifier: Framework :: FastAPI
Classifier: Framework :: Flask
Classifier: Intended Audience :: Developers
Classifier: License :: OSI Approved :: Apache Software License
Classifier: Programming Language :: Python :: 3 :: Only
Classifier: Programming Language :: Python :: 3.10
Classifier: Programming Language :: Python :: 3.11
Classifier: Programming Language :: Python :: 3.12
Classifier: Topic :: Software Development :: Libraries :: Application Frameworks
Classifier: Topic :: Utilities
Requires-Python: >=3.9
Requires-Dist: fastapi>=0.110
Requires-Dist: jinja2>=3.1
Requires-Dist: pydantic-settings>=2.10
Requires-Dist: pydantic>=2.6
Requires-Dist: python-dotenv>=1.0
Requires-Dist: pyyaml>=6.0
Requires-Dist: requests>=2.31
Requires-Dist: rich>=13.7
Requires-Dist: structlog>=23.2
Requires-Dist: typer>=0.12
Requires-Dist: uvicorn>=0.29
Provides-Extra: dev
Requires-Dist: black>=24.4; extra == 'dev'
Requires-Dist: isort>=5.0; extra == 'dev'
Requires-Dist: mkdocs-material>=9.5; extra == 'dev'
Requires-Dist: mkdocs>=1.6; extra == 'dev'
Requires-Dist: mypy>=1.10; extra == 'dev'
Requires-Dist: pre-commit>=3.7; extra == 'dev'
Requires-Dist: pytest-xdist>=3.5; extra == 'dev'
Requires-Dist: pytest>=8.2; extra == 'dev'
Requires-Dist: ruff>=0.4; extra == 'dev'
Provides-Extra: openai
Requires-Dist: openai>=1.30; extra == 'openai'
Requires-Dist: tiktoken>=0.3.0; extra == 'openai'
Provides-Extra: web
Requires-Dist: flask>=3.0; extra == 'web'
Requires-Dist: gunicorn>=21.2; extra == 'web'
Requires-Dist: jinja2>=3.1; extra == 'web'
